LICENSE.txt
MANIFEST.in
README.md
setup.py
iml_sos_plugin/__init__.py
iml_sos_plugin/cli.py
iml_sos_plugin/iml.py
iml_sos_plugin/scm_version.py
iml_sos_plugin.egg-info/PKG-INFO
iml_sos_plugin.egg-info/SOURCES.txt
iml_sos_plugin.egg-info/dependency_links.txt
iml_sos_plugin.egg-info/entry_points.txt
iml_sos_plugin.egg-info/top_level.txt