Metadata-Version: 1.1
Name: iml-sos-plugin
Version: 2.3.0
Summary: IML sosreport plugin
Home-page: https://pypi.python.org/pypi/iml_sos_plugin
Author: Whamcloud
Author-email: iml@whamcloud.com
License: MIT
Keywords: IML lustre high-availability
Platform: UNKNOWN
Classifier: Development Status :: 5 - Production/Stable
Classifier: License :: OSI Approved :: MIT License
Classifier: Programming Language :: Python :: 2
Classifier: Programming Language :: Python :: 2.7
